pyalveo/__init__.py
pyalveo/cache.py
pyalveo/objects.py
pyalveo/pyalveo.py
pyalveo-1.1.dist-info/LICENSE.txt
pyalveo-1.1.dist-info/METADATA
pyalveo-1.1.dist-info/WHEEL
pyalveo-1.1.dist-info/top_level.txt
pyalveo-1.1.dist-info/RECORD
