Metadata-Version: 2.1
Name: pyalveo
Version: 1.1
Summary: A Python library for interfacing with the Alveo API
Home-page: https://github.com/Alveo/pyalveo
Maintainer: Steve Cassidy
Maintainer-email: Steve.Cassidy@mq.edu.au
License: BSD
Keywords: alveo hcsvlab python library
Platform: UNKNOWN
Requires-Dist: python-dateutil
Requires-Dist: requests
Requires-Dist: oauthlib
Requires-Dist: requests-oauthlib
